flashplot/__init__.py
flashplot/flashplot.py
flashplot-0.0.6.dist-info/licenses/LICENSE
flashplot-0.0.6.dist-info/METADATA
flashplot-0.0.6.dist-info/WHEEL
flashplot-0.0.6.dist-info/top_level.txt
flashplot-0.0.6.dist-info/RECORD
