Metadata-Version: 2.4
Name: flashplot
Version: 0.0.6
Requires-Python: >=3.11
License-File: LICENSE
Requires-Dist: numpy
Requires-Dist: matplotlib
Requires-Dist: pillow
Requires-Dist: tqdm>=4.67.1
Dynamic: license-file
